groups_manager/__init__.py
groups_manager/admin.py
groups_manager/exceptions_gm.py
groups_manager/forms.py
groups_manager/models.py
groups_manager/perms.py
groups_manager/settings.py
groups_manager/urls.py
groups_manager/utils.py
groups_manager/views.py
groups_manager/migrations/0001_initial.py
groups_manager/migrations/0002_0_4_3_remove_m2m_null.py
groups_manager/migrations/0003_0_5_0_rename_reverse_relations_with_vars.py
groups_manager/migrations/0004_0_6_0_groupmember_expiration_date.py
groups_manager/migrations/0005_0_6_2_verbose_name_expiration_date.py
groups_manager/migrations/0006_1_0_0_default.py
groups_manager/migrations/0007_1_2_0_alter_group_group_entities_alter_group_group_members_and_more.py
groups_manager/migrations/0008_1_3_0_jsonfield_from_django.py
groups_manager/migrations/__init__.py
groups_manager/static/groups_manager/css/groups_manager.css
groups_manager/static/groups_manager/css/icons/groups_manager.css
groups_manager/static/groups_manager/css/icons/groups_manager.eot
groups_manager/static/groups_manager/css/icons/groups_manager.svg
groups_manager/static/groups_manager/css/icons/groups_manager.ttf
groups_manager/static/groups_manager/css/icons/groups_manager.woff
groups_manager/static/groups_manager/js/groups_manager.js
groups_manager/templates/groups_manager/bootstrap3/form_template.html
groups_manager/templates/groups_manager/bootstrap3/group.html
groups_manager/templates/groups_manager/bootstrap3/group_confirm_delete.html
groups_manager/templates/groups_manager/bootstrap3/group_detail.html
groups_manager/templates/groups_manager/bootstrap3/group_entity.html
groups_manager/templates/groups_manager/bootstrap3/group_entity_confirm_delete.html
groups_manager/templates/groups_manager/bootstrap3/group_entity_detail.html
groups_manager/templates/groups_manager/bootstrap3/group_entity_form.html
groups_manager/templates/groups_manager/bootstrap3/group_entity_list.html
groups_manager/templates/groups_manager/bootstrap3/group_form.html
django_groups_manager-1.3.0.dist-info/AUTHORS
django_groups_manager-1.3.0.dist-info/LICENSE
django_groups_manager-1.3.0.dist-info/METADATA
django_groups_manager-1.3.0.dist-info/WHEEL
django_groups_manager-1.3.0.dist-info/top_level.txt
django_groups_manager-1.3.0.dist-info/RECORD
