Metadata-Version: 2.1
Name: django-groups-manager
Version: 1.3.0
Summary: Django groups manager through django-mptt.
Home-page: https://github.com/vittoriozamboni/django-groups-manager
Author: Vittorio Zamboni
Author-email: vittorio.zamboni@gmail.com
License: MIT
Platform: UNKNOWN
Classifier: Development Status :: 5 - Production/Stable
Classifier: Environment :: Web Environment
Classifier: Framework :: Django
Classifier: Intended Audience :: Developers
Classifier: License :: OSI Approved :: MIT License
Classifier: Operating System :: OS Independent
Classifier: Programming Language :: Python
Classifier: Programming Language :: Python :: 3
Classifier: Programming Language :: Python :: 3.8
Classifier: Programming Language :: Python :: 3.9
Classifier: Programming Language :: Python :: 3.10
Classifier: Programming Language :: Python :: 3.11
Classifier: Topic :: Security
License-File: LICENSE
License-File: AUTHORS
Requires-Dist: django (>=3.2)
Requires-Dist: django-mptt
